leaderboardweb/__init__.py
leaderboardweb/static/asset-manifest.json
leaderboardweb/static/favicon.ico
leaderboardweb/static/index.html
leaderboardweb/static/images/ProtossIcon.png
leaderboardweb/static/images/TerranIcon.png
leaderboardweb/static/images/ZergIcon.png
leaderboardweb/static/images/allin_official.png
leaderboardweb/static/images/bronze.png
leaderboardweb/static/images/diamond.png
leaderboardweb/static/images/gold.png
leaderboardweb/static/images/grandmaster.png
leaderboardweb/static/images/master.png
leaderboardweb/static/images/platinum.png
leaderboardweb/static/images/silver.png
leaderboardweb/static/static/css/main.39fc96a2.css
leaderboardweb/static/static/css/main.39fc96a2.css.map
leaderboardweb/static/static/js/main.4b4242d0.js
leaderboardweb/static/static/js/main.4b4242d0.js.map
leaderboardweb-0.0.7.dist-info/METADATA
leaderboardweb-0.0.7.dist-info/RECORD
leaderboardweb-0.0.7.dist-info/WHEEL
leaderboardweb-0.0.7.dist-info/top_level.txt
