Metadata-Version: 2.1
Name: leaderboardweb
Version: 0.0.7
Summary: Frontend for All Inspiration Clan Leaderboard
Home-page: https://github.com/frugs/allin-web
Author: Hugo Wainwright
Author-email: wainwrighthugo@gmail.com
License: UNKNOWN
Keywords: sc2,MMR
Platform: UNKNOWN
Requires-Dist: flask
